uspec.py
uspec-1.0.24.data/scripts/uspec
uspec-1.0.24.dist-info/LICENSE
uspec-1.0.24.dist-info/METADATA
uspec-1.0.24.dist-info/WHEEL
uspec-1.0.24.dist-info/top_level.txt
uspec-1.0.24.dist-info/RECORD
