Metadata-Version: 2.1
Name: uspec
Version: 1.0.24
Summary: RSpec like behavior driven development (BDD) tool based on unittest
Home-page: https://github.com/MountainField/uspec
Download-URL: https://github.com/MountainField/uspec/releases
Author: Takahide Nogayama
Author-email: NOGAYAMA@gmail.com
License: MIT
Classifier: Development Status :: 4 - Beta
Classifier: Environment :: Console
Classifier: Intended Audience :: Developers
Classifier: License :: OSI Approved :: MIT License
Classifier: Operating System :: OS Independent
Classifier: Topic :: Documentation
Classifier: Topic :: Software Development :: Documentation
Classifier: Topic :: Software Development :: Quality Assurance
Classifier: Topic :: Software Development :: Testing
Classifier: Programming Language :: Python
Classifier: Programming Language :: Python :: 3
Requires-Python: >=3.0
License-File: LICENSE
